LICENSE.txt
MANIFEST.in
setup.cfg
setup.py
audit/__init__.py
lraudit.egg-info/PKG-INFO
lraudit.egg-info/SOURCES.txt
lraudit.egg-info/dependency_links.txt
lraudit.egg-info/not-zip-safe
lraudit.egg-info/top_level.txt