Metadata-Version: 1.0
Name: lraudit
Version: 0.1.1
Summary: Adds auditing to LR Flask apps
Home-page: http://github.com/LandRegistry/audit-plugin
Author: Land Registry
Author-email: lr-dev@example.org
License: MIT
Platform: any
